fowt_force_gen/__init__.py
fowt_force_gen/buoy.py
fowt_force_gen/fast_io.py
fowt_force_gen/filegen.py
fowt_force_gen/force_gen.py
fowt_force_gen/moortune.py
fowt_force_gen/parse.py
fowt_force_gen/post_fast.py
fowt_force_gen/pre_fast.py
fowt_force_gen/run_fast.py
fowt_force_gen/windbins.py
fowt_force_gen/.filepaths/fast_file_path.txt
fowt_force_gen/.filepaths/turbsim_file_path.txt
fowt_force_gen/example_files/example1_MoorDyn.dat
fowt_force_gen/example_files/example4.dat
fowt_force_gen/example_files/post-fast/example2_11.62mps_0deg_Climate0.MD.Line1.out
fowt_force_gen/example_files/post-fast/example2_11.62mps_0deg_Climate0.MD.Line2.out
fowt_force_gen/example_files/post-fast/example2_11.62mps_0deg_Climate0.MD.Line3.out
fowt_force_gen/example_files/post-fast/example2_11.62mps_0deg_Climate0.outb
fowt_force_gen/example_files/post-fast/example2_14.94mps_180deg_Climate1.MD.Line1.out
fowt_force_gen/example_files/post-fast/example2_14.94mps_180deg_Climate1.MD.Line2.out
fowt_force_gen/example_files/post-fast/example2_14.94mps_180deg_Climate1.MD.Line3.out
fowt_force_gen/example_files/post-fast/example2_14.94mps_180deg_Climate1.outb
fowt_force_gen/fast_input_files/NRELOffshrBsline5MW_AeroDyn_blade.dat
fowt_force_gen/fast_input_files/NRELOffshrBsline5MW_Blade.dat
fowt_force_gen/fast_input_files/NRELOffshrBsline5MW_OC3Hywind_AeroDyn15.dat
fowt_force_gen/fast_input_files/OC3Hywind_ElastoDyn.dat
fowt_force_gen/fast_input_files/OC3Hywind_ElastoDyn_Tower.dat
fowt_force_gen/fast_input_files/OC3Hywind_ServoDyn.dat
fowt_force_gen/fast_input_files/OC4Semi_ElastoDyn.dat
fowt_force_gen/fast_input_files/OC4Semi_ElastoDyn_Tower.dat
fowt_force_gen/fast_input_files/OC4Semi_ServoDyn.dat
fowt_force_gen/fast_input_files/AeroData/Cylinder1.dat
fowt_force_gen/fast_input_files/AeroData/Cylinder2.dat
fowt_force_gen/fast_input_files/AeroData/DU21_A17.dat
fowt_force_gen/fast_input_files/AeroData/DU25_A17.dat
fowt_force_gen/fast_input_files/AeroData/DU30_A17.dat
fowt_force_gen-0.1.0.dist-info/LICENSE
fowt_force_gen-0.1.0.dist-info/METADATA
fowt_force_gen-0.1.0.dist-info/WHEEL
fowt_force_gen-0.1.0.dist-info/top_level.txt
fowt_force_gen-0.1.0.dist-info/RECORD
