Metadata-Version: 2.1
Name: fowt-force-gen
Version: 0.1.0
Summary: A package to use OpenFAST to simulate a floating wind turbine at a certain location
Home-page: https://github.com/michaelcdevin/fowt_force_gen
Author: Michael Devin
Author-email: michaelcdevin@outlook.com
License: MIT License
Platform: UNKNOWN
Classifier: Programming Language :: Python :: 3
Classifier: License :: OSI Approved :: MIT License
Classifier: Operating System :: OS Independent
Classifier: Intended Audience :: Science/Research
Classifier: Natural Language :: English
Requires-Python: >=3
